[
    {
        "date": "23 January 2024 08:35:15",
        "duration": 2700,
        "distance": 12400,
        "avg_speed": 17.33,
        "altitude_diff": 24,
        "positions": [
            {"lng": "11.12177", "lat": "46.06798", "alt": "50"},
            {"lng": "11.12400", "lat": "46.06950", "alt": "55"},
            {"lng": "11.12715", "lat": "46.06774", "alt": "52"},
            {"lng": "11.12900", "lat": "46.06583", "alt": "53"},
            {"lng": "11.13057", "lat": "46.06371", "alt": "51"},
            {"lng": "11.13180", "lat": "46.06230", "alt": "50"},
            {"lng": "11.13285", "lat": "46.06006", "alt": "55"}
        ]
    },
    {
        "date": "25 January 2024 12:45:30",
        "duration": 2880,
        "distance": 14200,
        "avg_speed": 17.71,
        "altitude_diff": 30,
        "positions": [
            {"lng": "11.12500", "lat": "46.07100", "alt": "200"},
            {"lng": "11.12850", "lat": "46.07280", "alt": "205"},
            {"lng": "11.13500", "lat": "46.07000", "alt": "210"},
            {"lng": "11.13850", "lat": "46.06900", "alt": "220"},
            {"lng": "11.14500", "lat": "46.06600", "alt": "225"},
            {"lng": "11.14950", "lat": "46.06400", "alt": "230"},
            {"lng": "11.15500", "lat": "46.06200", "alt": "235"}
        ]
    },
    {
        "date": "26 January 2024 18:15:00",
        "duration": 2520,
        "distance": 10800,
        "avg_speed": 15.71,
        "altitude_diff": 20,
        "positions": [
            {"lng": "11.13500", "lat": "46.06800", "alt": "210"},
            {"lng": "11.13700", "lat": "46.06950", "alt": "220"},
            {"lng": "11.14200", "lat": "46.06600", "alt": "225"},
            {"lng": "11.14700", "lat": "46.06500", "alt": "230"},
            {"lng": "11.15200", "lat": "46.06200", "alt": "235"},
            {"lng": "11.15650", "lat": "46.06050", "alt": "240"},
            {"lng": "11.16500", "lat": "46.05800", "alt": "245"}
        ]
    },
    {
        "date": "27 January 2024 07:30:45",
        "duration": 2400,
        "distance": 11000,
        "avg_speed": 15.5,
        "altitude_diff": 18,
        "positions": [
            {"lng": "11.12200", "lat": "46.06700", "alt": "200"},
            {"lng": "11.12400", "lat": "46.06680", "alt": "205"},
            {"lng": "11.12500", "lat": "46.06650", "alt": "210"},
            {"lng": "11.12650", "lat": "46.06520", "alt": "215"},
            {"lng": "11.12450", "lat": "46.06440", "alt": "220"},
            {"lng": "11.12250", "lat": "46.06400", "alt": "225"},
            {"lng": "11.12100", "lat": "46.06440", "alt": "230"},
            {"lng": "11.12080", "lat": "46.06520", "alt": "235"},
            {"lng": "11.12160", "lat": "46.06600", "alt": "240"}
        ]
    },
    {
        "date": "28 January 2024 15:20:10",
        "duration": 3000,
        "distance": 13000,
        "avg_speed": 18.5,
        "altitude_diff": 26,
        "positions": [
            {"lng": "11.12950", "lat": "46.06950", "alt": "210"},
            {"lng": "11.13250", "lat": "46.07100", "alt": "215"},
            {"lng": "11.13650", "lat": "46.06800", "alt": "220"},
            {"lng": "11.14100", "lat": "46.06600", "alt": "225"},
            {"lng": "11.14500", "lat": "46.06400", "alt": "230"},
            {"lng": "11.15000", "lat": "46.06200", "alt": "235"},
            {"lng": "11.15500", "lat": "46.06000", "alt": "240"}
        ]
    },
    {
        "date": "29 January 2024 09:10:55",
        "duration": 3240,
        "distance": 15000,
        "avg_speed": 19.44,
        "altitude_diff": 32,
        "positions": [
            {"lng": "11.12500", "lat": "46.07200", "alt": "200"},
            {"lng": "11.12850", "lat": "46.07400", "alt": "205"},
            {"lng": "11.13500", "lat": "46.07100", "alt": "210"},
            {"lng": "11.13850", "lat": "46.06900", "alt": "220"},
            {"lng": "11.14500", "lat": "46.06700", "alt": "225"},
            {"lng": "11.15000", "lat": "46.06500", "alt": "230"},
            {"lng": "11.15500", "lat": "46.06300", "alt": "235"}
        ]
    },
    {
        "date": "30 January 2024 14:55:40",
        "duration": 2640,
        "distance": 11500,
        "avg_speed": 16.36,
        "altitude_diff": 22,
        "positions": [
            {"lng": "11.13500", "lat": "46.06700", "alt": "210"},
            {"lng": "11.14000", "lat": "46.06900", "alt": "220"},
            {"lng": "11.14500", "lat": "46.06500", "alt": "225"},
            {"lng": "11.15000", "lat": "46.06300", "alt": "230"},
            {"lng": "11.15500", "lat": "46.06100", "alt": "235"},
            {"lng": "11.16000", "lat": "46.05900", "alt": "240"},
            {"lng": "11.16500", "lat": "46.05700", "alt": "245"}
        ]
    },
    {
    "date": "1 February 2024 09:40:15",
    "duration": 2880,
    "distance": 14000,
    "avg_speed": 18.33,
    "altitude_diff": 25,
    "positions": [
        {"lng": "11.120", "lat": "46.066", "alt": "200"},
        {"lng": "11.124", "lat": "46.068", "alt": "205"},
        {"lng": "11.129", "lat": "46.070", "alt": "210"},
        {"lng": "11.134", "lat": "46.072", "alt": "215"},
        {"lng": "11.139", "lat": "46.074", "alt": "220"},
        {"lng": "11.144", "lat": "46.076", "alt": "225"},
        {"lng": "11.148", "lat": "46.078", "alt": "230"}
    ]
}
]
