[
    {
        "date": "23 January 2024 08:35:15",
        "duration": 2700,
        "distance": 12400,
        "avg_speed": 17.33,
        "altitude_diff": 24,
        "positions": [
            {"lng": "11.12177", "lat": "46.06798", "alt": "50"},
            {"lng": "11.12400", "lat": "46.06950", "alt": "55"},
            {"lng": "11.12715", "lat": "46.06774", "alt": "52"},
            {"lng": "11.12900", "lat": "46.06583", "alt": "53"},
            {"lng": "11.13057", "lat": "46.06371", "alt": "51"},
            {"lng": "11.13180", "lat": "46.06230", "alt": "50"},
            {"lng": "11.13285", "lat": "46.06006", "alt": "55"}
        ]
    },
    {
        "date": "25 January 2024 12:45:30",
        "duration": 2880,
        "distance": 14200,
        "avg_speed": 17.71,
        "altitude_diff": 30,
        "positions": [
            {"lng": "11.12500", "lat": "46.07100", "alt": "200"},
            {"lng": "11.12850", "lat": "46.07280", "alt": "205"},
            {"lng": "11.13500", "lat": "46.07000", "alt": "210"},
            {"lng": "11.13850", "lat": "46.06900", "alt": "220"},
            {"lng": "11.14500", "lat": "46.06600", "alt": "225"},
            {"lng": "11.14950", "lat": "46.06400", "alt": "230"},
            {"lng": "11.15500", "lat": "46.06200", "alt": "235"}
        ]
    },
    {
        "date": "26 January 2024 18:15:00",
        "duration": 2520,
        "distance": 10800,
        "avg_speed": 15.71,
        "altitude_diff": 20,
        "positions": [
            {"lng": "11.13500", "lat": "46.06800", "alt": "210"},
            {"lng": "11.13700", "lat": "46.06950", "alt": "220"},
            {"lng": "11.14200", "lat": "46.06600", "alt": "225"},
            {"lng": "11.14700", "lat": "46.06500", "alt": "230"},
            {"lng": "11.15200", "lat": "46.06200", "alt": "235"},
            {"lng": "11.15650", "lat": "46.06050", "alt": "240"},
            {"lng": "11.16500", "lat": "46.05800", "alt": "245"}
        ]
    },
    {
        "date": "27 January 2024 07:30:45",
        "duration": 2400,
        "distance": 11000,
        "avg_speed": 15.5,
        "altitude_diff": 18,
        "positions": [
            {"lng": "11.12200", "lat": "46.06700", "alt": "200"},
            {"lng": "11.12400", "lat": "46.06680", "alt": "205"},
            {"lng": "11.12500", "lat": "46.06650", "alt": "210"},
            {"lng": "11.12650", "lat": "46.06520", "alt": "215"},
            {"lng": "11.12450", "lat": "46.06440", "alt": "220"},
            {"lng": "11.12250", "lat": "46.06400", "alt": "225"},
            {"lng": "11.12100", "lat": "46.06440", "alt": "230"},
            {"lng": "11.12080", "lat": "46.06520", "alt": "235"},
            {"lng": "11.12160", "lat": "46.06600", "alt": "240"}
        ]
    },
    {
        "date": "30 January 2024 14:55:40",
        "duration": 2640,
        "distance": 11500,
        "avg_speed": 16.36,
        "altitude_diff": 22,
        "positions": [
            {"lng": "11.13500", "lat": "46.06700", "alt": "210"},
            {"lng": "11.14000", "lat": "46.06900", "alt": "220"},
            {"lng": "11.14500", "lat": "46.06500", "alt": "225"},
            {"lng": "11.15000", "lat": "46.06300", "alt": "230"},
            {"lng": "11.15500", "lat": "46.06100", "alt": "235"},
            {"lng": "11.16000", "lat": "46.05900", "alt": "240"},
            {"lng": "11.16500", "lat": "46.05700", "alt": "245"}
        ]
    },
    {
    "date": "2 February 2024 10:15:30",
    "duration": 2500,
    "distance": 11500,
    "avg_speed": 15.2,
    "altitude_diff": 20,
    "positions": [
        {"lng": "11.12150", "lat": "46.06750", "alt": "200"},
        {"lng": "11.12350", "lat": "46.06720", "alt": "205"},
        {"lng": "11.12450", "lat": "46.06680", "alt": "210"},
        {"lng": "11.12600", "lat": "46.06550", "alt": "215"},
        {"lng": "11.12480", "lat": "46.06480", "alt": "220"},
        {"lng": "11.12300", "lat": "46.06450", "alt": "225"},
        {"lng": "11.12180", "lat": "46.06480", "alt": "230"},
        {"lng": "11.12120", "lat": "46.06550", "alt": "235"},
        {"lng": "11.12200", "lat": "46.06620", "alt": "240"}
    ]
},
    {
    "date": "3 February 2024 08:45:00",
    "duration": 3000,
    "distance": 14000,
    "avg_speed": 16.7,
    "altitude_diff": 25,
    "positions": [
        {"lng": "11.120", "lat": "46.067", "alt": "200"},
        {"lng": "11.122", "lat": "46.068", "alt": "205"},
        {"lng": "11.124", "lat": "46.069", "alt": "210"},
        {"lng": "11.126", "lat": "46.070", "alt": "215"},
        {"lng": "11.128", "lat": "46.071", "alt": "220"},
        {"lng": "11.130", "lat": "46.072", "alt": "225"},
        {"lng": "11.132", "lat": "46.073", "alt": "230"},
        {"lng": "11.134", "lat": "46.074", "alt": "235"},
        {"lng": "11.136", "lat": "46.075", "alt": "240"},
        {"lng": "11.138", "lat": "46.076", "alt": "245"},
        {"lng": "11.140", "lat": "46.077", "alt": "250"},
        {"lng": "11.142", "lat": "46.078", "alt": "255"},
        {"lng": "11.144", "lat": "46.079", "alt": "260"},
        {"lng": "11.146", "lat": "46.080", "alt": "265"},
        {"lng": "11.148", "lat": "46.081", "alt": "270"},
        {"lng": "11.150", "lat": "46.082", "alt": "275"},
        {"lng": "11.152", "lat": "46.083", "alt": "280"},
        {"lng": "11.154", "lat": "46.084", "alt": "285"},
        {"lng": "11.156", "lat": "46.085", "alt": "290"},
        {"lng": "11.158", "lat": "46.086", "alt": "295"},
        {"lng": "11.160", "lat": "46.087", "alt": "300"},
        {"lng": "11.162", "lat": "46.088", "alt": "305"},
        {"lng": "11.164", "lat": "46.089", "alt": "310"},
        {"lng": "11.166", "lat": "46.090", "alt": "315"},
        {"lng": "11.168", "lat": "46.091", "alt": "320"},
        {"lng": "11.170", "lat": "46.092", "alt": "325"},
        {"lng": "11.172", "lat": "46.093", "alt": "330"},
        {"lng": "11.174", "lat": "46.094", "alt": "335"},
        {"lng": "11.176", "lat": "46.095", "alt": "340"},
        {"lng": "11.178", "lat": "46.096", "alt": "345"},
        {"lng": "11.180", "lat": "46.097", "alt": "350"},
        {"lng": "11.182", "lat": "46.098", "alt": "355"},
        {"lng": "11.184", "lat": "46.099", "alt": "360"},
        {"lng": "11.186", "lat": "46.100", "alt": "365"},
        {"lng": "11.188", "lat": "46.101", "alt": "370"},
        {"lng": "11.190", "lat": "46.102", "alt": "375"},
        {"lng": "11.192", "lat": "46.103", "alt": "380"},
        {"lng": "11.194", "lat": "46.104", "alt": "385"},
        {"lng": "11.196", "lat": "46.105", "alt": "390"},
        {"lng": "11.198", "lat": "46.106", "alt": "395"},
        {"lng": "11.200", "lat": "46.107", "alt": "400"},
        {"lng": "11.202", "lat": "46.108", "alt": "405"},
        {"lng": "11.204", "lat": "46.109", "alt": "410"},
        {"lng": "11.206", "lat": "46.110", "alt": "415"},
        {"lng": "11.208", "lat": "46.111", "alt": "420"},
        {"lng": "11.210", "lat": "46.112", "alt": "425"},
        {"lng": "11.212", "lat": "46.113", "alt": "430"},
        {"lng": "11.214", "lat": "46.114", "alt": "435"},
        {"lng": "11.216", "lat": "46.115", "alt": "440"},
        {"lng": "11.218", "lat": "46.116", "alt": "445"},
        {"lng": "11.220", "lat": "46.117", "alt": "450"}
    ]
},{
    "date": "3 February 2024 08:45:00",
    "duration": 3000,
    "distance": 14000,
    "avg_speed": 16.7,
    "altitude_diff": 25,
    "positions": [
        {"lng": "11.122", "lat": "46.068", "alt": "200"},
        {"lng": "11.124", "lat": "46.069", "alt": "205"},
        {"lng": "11.126", "lat": "46.071", "alt": "210"},
        {"lng": "11.128", "lat": "46.072", "alt": "215"},
        {"lng": "11.130", "lat": "46.073", "alt": "220"},
        {"lng": "11.132", "lat": "46.074", "alt": "225"},
        {"lng": "11.134", "lat": "46.075", "alt": "230"},
        {"lng": "11.136", "lat": "46.076", "alt": "235"},
        {"lng": "11.138", "lat": "46.077", "alt": "240"},
        {"lng": "11.140", "lat": "46.078", "alt": "245"},
        {"lng": "11.142", "lat": "46.079", "alt": "250"},
        {"lng": "11.144", "lat": "46.080", "alt": "255"},
        {"lng": "11.146", "lat": "46.081", "alt": "260"},
        {"lng": "11.148", "lat": "46.082", "alt": "265"},
        {"lng": "11.150", "lat": "46.083", "alt": "270"},
        {"lng": "11.152", "lat": "46.084", "alt": "275"},
        {"lng": "11.154", "lat": "46.085", "alt": "280"},
        {"lng": "11.156", "lat": "46.086", "alt": "285"},
        {"lng": "11.158", "lat": "46.087", "alt": "290"},
        {"lng": "11.160", "lat": "46.088", "alt": "295"},
        {"lng": "11.162", "lat": "46.089", "alt": "300"},
        {"lng": "11.164", "lat": "46.090", "alt": "305"},
        {"lng": "11.166", "lat": "46.091", "alt": "310"},
        {"lng": "11.168", "lat": "46.092", "alt": "315"},
        {"lng": "11.170", "lat": "46.093", "alt": "320"},
        {"lng": "11.172", "lat": "46.094", "alt": "325"},
        {"lng": "11.174", "lat": "46.095", "alt": "330"},
        {"lng": "11.176", "lat": "46.096", "alt": "335"},
        {"lng": "11.178", "lat": "46.097", "alt": "340"},
        {"lng": "11.180", "lat": "46.098", "alt": "345"},
        {"lng": "11.182", "lat": "46.099", "alt": "350"},
        {"lng": "11.184", "lat": "46.100", "alt": "355"},
        {"lng": "11.186", "lat": "46.101", "alt": "360"},
        {"lng": "11.188", "lat": "46.102", "alt": "365"},
        {"lng": "11.190", "lat": "46.103", "alt": "370"},
        {"lng": "11.192", "lat": "46.104", "alt": "375"},
        {"lng": "11.194", "lat": "46.105", "alt": "380"},
        {"lng": "11.196", "lat": "46.106", "alt": "385"},
        {"lng": "11.198", "lat": "46.107", "alt": "390"},
        {"lng": "11.200", "lat": "46.108", "alt": "395"},
        {"lng": "11.202", "lat": "46.109", "alt": "400"},
        {"lng": "11.204", "lat": "46.110", "alt": "405"},
        {"lng": "11.206", "lat": "46.111", "alt": "410"},
        {"lng": "11.208", "lat": "46.112", "alt": "415"},
        {"lng": "11.210", "lat": "46.113", "alt": "420"},
        {"lng": "11.212", "lat": "46.114", "alt": "425"},
        {"lng": "11.214", "lat": "46.115", "alt": "430"},
        {"lng": "11.216", "lat": "46.116", "alt": "435"},
        {"lng": "11.218", "lat": "46.117", "alt": "440"},
        {"lng": "11.220", "lat": "46.118", "alt": "445"},
        {"lng": "11.222", "lat": "46.119", "alt": "450"}
    ]
},
    {
    "date": "4 February 2024 07:30:00",
    "duration": 3200,
    "distance": 16000,
    "avg_speed": 15.0,
    "altitude_diff": 15,
    "positions": [
        {"lng": "11.120", "lat": "46.069", "alt": "200"},
        {"lng": "11.121", "lat": "46.070", "alt": "205"},
        {"lng": "11.122", "lat": "46.071", "alt": "210"},
        {"lng": "11.123", "lat": "46.072", "alt": "215"},
        {"lng": "11.124", "lat": "46.073", "alt": "220"},
        {"lng": "11.125", "lat": "46.074", "alt": "225"},
        {"lng": "11.126", "lat": "46.075", "alt": "230"},
        {"lng": "11.127", "lat": "46.076", "alt": "235"},
        {"lng": "11.128", "lat": "46.077", "alt": "240"},
        {"lng": "11.129", "lat": "46.078", "alt": "245"},
        {"lng": "11.130", "lat": "46.079", "alt": "250"},
        {"lng": "11.131", "lat": "46.080", "alt": "255"},
        {"lng": "11.132", "lat": "46.081", "alt": "260"},
        {"lng": "11.133", "lat": "46.082", "alt": "265"},
        {"lng": "11.134", "lat": "46.083", "alt": "270"},
        {"lng": "11.135", "lat": "46.084", "alt": "275"},
        {"lng": "11.136", "lat": "46.085", "alt": "280"},
        {"lng": "11.137", "lat": "46.086", "alt": "285"},
        {"lng": "11.138", "lat": "46.087", "alt": "290"},
        {"lng": "11.139", "lat": "46.088", "alt": "295"},
        {"lng": "11.140", "lat": "46.089", "alt": "300"},
        {"lng": "11.141", "lat": "46.090", "alt": "305"},
        {"lng": "11.142", "lat": "46.091", "alt": "310"},
        {"lng": "11.143", "lat": "46.092", "alt": "315"},
        {"lng": "11.144", "lat": "46.093", "alt": "320"},
        {"lng": "11.145", "lat": "46.094", "alt": "325"},
        {"lng": "11.146", "lat": "46.095", "alt": "330"},
        {"lng": "11.147", "lat": "46.096", "alt": "335"},
        {"lng": "11.148", "lat": "46.097", "alt": "340"},
        {"lng": "11.149", "lat": "46.098", "alt": "345"},
        {"lng": "11.150", "lat": "46.099", "alt": "350"},
        {"lng": "11.151", "lat": "46.100", "alt": "355"},
        {"lng": "11.152", "lat": "46.101", "alt": "360"},
        {"lng": "11.153", "lat": "46.102", "alt": "365"},
        {"lng": "11.154", "lat": "46.103", "alt": "370"},
        {"lng": "11.155", "lat": "46.104", "alt": "375"},
        {"lng": "11.156", "lat": "46.105", "alt": "380"},
        {"lng": "11.157", "lat": "46.106", "alt": "385"},
        {"lng": "11.158", "lat": "46.107", "alt": "390"},
        {"lng": "11.159", "lat": "46.108", "alt": "395"},
        {"lng": "11.160", "lat": "46.109", "alt": "400"},
        {"lng": "11.161", "lat": "46.110", "alt": "405"},
        {"lng": "11.162", "lat": "46.111", "alt": "410"},
        {"lng": "11.163", "lat": "46.112", "alt": "415"},
        {"lng": "11.164", "lat": "46.113", "alt": "420"},
        {"lng": "11.165", "lat": "46.114", "alt": "425"},
        {"lng": "11.166", "lat": "46.115", "alt": "430"},
        {"lng": "11.167", "lat": "46.116", "alt": "435"},
        {"lng": "11.168", "lat": "46.117", "alt": "440"},
        {"lng": "11.169", "lat": "46.118", "alt": "445"},
        {"lng": "11.170", "lat": "46.119", "alt": "450"}
    ]
}
,
    {
    "date": "5 February 2024 09:00:00",
    "duration": 3500,
    "distance": 17000,
    "avg_speed": 14.8,
    "altitude_diff": 18,
    "positions": [
        {"lng": "11.120", "lat": "46.070", "alt": "200"},
        {"lng": "11.121", "lat": "46.071", "alt": "205"},
        {"lng": "11.122", "lat": "46.072", "alt": "210"},
        {"lng": "11.123", "lat": "46.073", "alt": "215"},
        {"lng": "11.124", "lat": "46.074", "alt": "220"},
        {"lng": "11.125", "lat": "46.075", "alt": "225"},
        {"lng": "11.126", "lat": "46.076", "alt": "230"},
        {"lng": "11.127", "lat": "46.077", "alt": "235"},
        {"lng": "11.128", "lat": "46.078", "alt": "240"},
        {"lng": "11.129", "lat": "46.079", "alt": "245"},
        {"lng": "11.130", "lat": "46.080", "alt": "250"},
        {"lng": "11.131", "lat": "46.081", "alt": "255"},
        {"lng": "11.132", "lat": "46.082", "alt": "260"},
        {"lng": "11.133", "lat": "46.083", "alt": "265"},
        {"lng": "11.134", "lat": "46.084", "alt": "270"},
        {"lng": "11.135", "lat": "46.085", "alt": "275"},
        {"lng": "11.136", "lat": "46.086", "alt": "280"},
        {"lng": "11.137", "lat": "46.087", "alt": "285"},
        {"lng": "11.138", "lat": "46.088", "alt": "290"},
        {"lng": "11.139", "lat": "46.089", "alt": "295"},
        {"lng": "11.140", "lat": "46.090", "alt": "300"},
        {"lng": "11.141", "lat": "46.091", "alt": "305"},
        {"lng": "11.142", "lat": "46.092", "alt": "310"},
        {"lng": "11.143", "lat": "46.093", "alt": "315"},
        {"lng": "11.144", "lat": "46.094", "alt": "320"},
        {"lng": "11.145", "lat": "46.095", "alt": "325"},
        {"lng": "11.146", "lat": "46.096", "alt": "330"},
        {"lng": "11.147", "lat": "46.097", "alt": "335"},
        {"lng": "11.148", "lat": "46.098", "alt": "340"},
        {"lng": "11.149", "lat": "46.099", "alt": "345"},
        {"lng": "11.150", "lat": "46.100", "alt": "350"},
        {"lng": "11.151", "lat": "46.101", "alt": "355"},
        {"lng": "11.152", "lat": "46.102", "alt": "360"},
        {"lng": "11.153", "lat": "46.103", "alt": "365"},
        {"lng": "11.154", "lat": "46.104", "alt": "370"},
        {"lng": "11.155", "lat": "46.105", "alt": "375"},
        {"lng": "11.156", "lat": "46.106", "alt": "380"},
        {"lng": "11.157", "lat": "46.107", "alt": "385"},
        {"lng": "11.158", "lat": "46.108", "alt": "390"},
        {"lng": "11.159", "lat": "46.109", "alt": "395"},
        {"lng": "11.160", "lat": "46.110", "alt": "400"},
        {"lng": "11.161", "lat": "46.111", "alt": "405"},
        {"lng": "11.162", "lat": "46.112", "alt": "410"},
        {"lng": "11.163", "lat": "46.113", "alt": "415"},
        {"lng": "11.164", "lat": "46.114", "alt": "420"},
        {"lng": "11.165", "lat": "46.115", "alt": "425"},
        {"lng": "11.166", "lat": "46.116", "alt": "430"},
        {"lng": "11.167", "lat": "46.117", "alt": "435"},
        {"lng": "11.168", "lat": "46.118", "alt": "440"},
        {"lng": "11.169", "lat": "46.119", "alt": "445"},
        {"lng": "11.170", "lat": "46.120", "alt": "450"}
    ]
},
    {
        "date": "27 January 2024 07:30:45",
        "duration": 2400,
        "distance": 11000,
        "avg_speed": 15.5,
        "altitude_diff": 18,
        "positions": [
            {"lng": "11.12200", "lat": "46.06700", "alt": "200"},
            {"lng": "11.12400", "lat": "46.06680", "alt": "205"},
            {"lng": "11.12500", "lat": "46.06650", "alt": "210"},
            {"lng": "11.12650", "lat": "46.06520", "alt": "215"},
            {"lng": "11.12450", "lat": "46.06440", "alt": "220"},
            {"lng": "11.12250", "lat": "46.06400", "alt": "225"},
            {"lng": "11.12100", "lat": "46.06440", "alt": "230"},
            {"lng": "11.12080", "lat": "46.06520", "alt": "235"},
            {"lng": "11.12160", "lat": "46.06600", "alt": "240"}
            {"lng": "11.12150", "lat": "46.06750", "alt": "200"},
        {"lng": "11.12350", "lat": "46.06720", "alt": "205"},
        {"lng": "11.12450", "lat": "46.06680", "alt": "210"},
        {"lng": "11.12600", "lat": "46.06550", "alt": "215"},
        {"lng": "11.12480", "lat": "46.06480", "alt": "220"},
        {"lng": "11.12300", "lat": "46.06450", "alt": "225"},
        {"lng": "11.12180", "lat": "46.06480", "alt": "230"},
        {"lng": "11.12120", "lat": "46.06550", "alt": "235"},
        {"lng": "11.12200", "lat": "46.06620", "alt": "240"}
    ]
}

    



]
